singleline_stroke3/__init__.py
singleline_stroke3/_modidx.py
singleline_stroke3/bounding_boxes.py
singleline_stroke3/dataset.py
singleline_stroke3/display.py
singleline_stroke3/e2e.py
singleline_stroke3/embeddings.py
singleline_stroke3/fileorg.py
singleline_stroke3/strokes.py
singleline_stroke3/svg.py
singleline_stroke3/tokenize.py
singleline_stroke3/transforms.py
singleline_stroke3-0.0.1.dist-info/LICENSE
singleline_stroke3-0.0.1.dist-info/METADATA
singleline_stroke3-0.0.1.dist-info/WHEEL
singleline_stroke3-0.0.1.dist-info/entry_points.txt
singleline_stroke3-0.0.1.dist-info/top_level.txt
singleline_stroke3-0.0.1.dist-info/RECORD
